contextrouter/.cursorrules
contextrouter/__init__.py
contextrouter/cli/__init__.py
contextrouter/cli/__main__.py
contextrouter/cli/app.py
contextrouter/cli/evals.py
contextrouter/cli/help.py
contextrouter/cli/rag.py
contextrouter/cli/registry.py
contextrouter/cli/commands/__init__.py
contextrouter/cli/ingest/__init__.py
contextrouter/cli/ingest/common.py
contextrouter/cli/ingest/deploy.py
contextrouter/cli/ingest/enrich.py
contextrouter/cli/ingest/export.py
contextrouter/cli/ingest/index.py
contextrouter/cli/ingest/ontology.py
contextrouter/cli/ingest/persona.py
contextrouter/cli/ingest/preprocess.py
contextrouter/cli/ingest/report.py
contextrouter/cli/ingest/run.py
contextrouter/cli/ingest/structure.py
contextrouter/core/__init__.py
contextrouter/core/bisquit.py
contextrouter/core/exceptions.py
contextrouter/core/flow_manager.py
contextrouter/core/interfaces.py
contextrouter/core/registry.py
contextrouter/core/state.py
contextrouter/core/tokens.py
contextrouter/core/types.py
contextrouter/core/config/__init__.py
contextrouter/core/config/base.py
contextrouter/core/config/ingestion.py
contextrouter/core/config/main.py
contextrouter/core/config/models.py
contextrouter/core/config/paths.py
contextrouter/core/config/providers.py
contextrouter/core/config/security.py
contextrouter/cortex/README.md
contextrouter/cortex/__init__.py
contextrouter/cortex/events.py
contextrouter/cortex/llm.py
contextrouter/cortex/models.py
contextrouter/cortex/state.py
contextrouter/cortex/callbacks/__init__.py
contextrouter/cortex/callbacks/tool_handler.py
contextrouter/cortex/evals/base.py
contextrouter/cortex/graphs/README.md
contextrouter/cortex/graphs/__init__.py
contextrouter/cortex/graphs/brain.py
contextrouter/cortex/graphs/rag_ingestion.py
contextrouter/cortex/graphs/rag_retrieval.py
contextrouter/cortex/nodes/__init__.py
contextrouter/cortex/nodes/utils.py
contextrouter/cortex/nodes/rag_retrieval/__init__.py
contextrouter/cortex/nodes/rag_retrieval/extract.py
contextrouter-0.11.1.dist-info/METADATA
contextrouter-0.11.1.dist-info/WHEEL
contextrouter-0.11.1.dist-info/entry_points.txt
contextrouter-0.11.1.dist-info/licenses/LICENSE.md
contextrouter-0.11.1.dist-info/RECORD
