Metadata-Version: 2.4
Name: contextrouter
Version: 0.11.1
Summary: Modular LangGraph-powered agentic brain for multi-source knowledge orchestration and RAG
Project-URL: Homepage, https://contextrouter.dev
Project-URL: Documentation, https://contextrouter.org
Project-URL: Repository, https://github.com/ContextRouter/contextrouter
Project-URL: Issues, https://github.com/ContextRouter/contextrouter/issues
Author-email: Pylypchuk Oleksii <oleksii.pylypchuk@tuta.com>
License:                                  Apache License
License-File: LICENSE.md
Classifier: Development Status :: 3 - Alpha
Classifier: License :: OSI Approved :: Apache Software License
Classifier: Programming Language :: Python :: 3 :: Only
Classifier: Programming Language :: Python :: 3.13
Classifier: Typing :: Typed
Requires-Python: >=3.13
Requires-Dist: click>=8.0.0
Requires-Dist: joblib>=1.5.3
Requires-Dist: langchain-community>=0.3.0
Requires-Dist: langchain-core>=0.3.0
Requires-Dist: langgraph>=0.2.0
Requires-Dist: pydantic>=2.0.0
Requires-Dist: python-dotenv>=1.0.0
Requires-Dist: rich>=13.0.0
Requires-Dist: tomli>=2.0.0
Requires-Dist: typer>=0.12.0
Provides-Extra: all
Requires-Dist: beautifulsoup4>=4.12.0; extra == 'all'
Requires-Dist: google-api-python-client<3.0.0,>=2.100.0; extra == 'all'
Requires-Dist: google-auth-oauthlib<2.0.0,>=1.2.0; extra == 'all'
Requires-Dist: google-auth<3.0.0,>=2.25.0; extra == 'all'
Requires-Dist: google-cloud-aiplatform>=1.0.0; extra == 'all'
Requires-Dist: google-cloud-discoveryengine>=0.13.0; extra == 'all'
Requires-Dist: google-cloud-firestore>=2.16.0; extra == 'all'
Requires-Dist: google-cloud-storage>=3.0.0; extra == 'all'
Requires-Dist: google-genai>=1.0.0; extra == 'all'
Requires-Dist: langchain-google-community>=2.0.0; extra == 'all'
Requires-Dist: langchain-google-genai>=2.0.0; extra == 'all'
Requires-Dist: langchain-google-vertexai>=2.0.0; extra == 'all'
Requires-Dist: langfuse>=2.0.0; extra == 'all'
Requires-Dist: networkx>=3.0; extra == 'all'
Requires-Dist: opentelemetry-instrumentation-threading>=0.48b0; extra == 'all'
Requires-Dist: psycopg-pool>=3.2.0; extra == 'all'
Requires-Dist: psycopg[binary]>=3.1.0; extra == 'all'
Requires-Dist: pymupdf-layout>=0.0.0; extra == 'all'
Requires-Dist: pymupdf4llm>=0.0.10; extra == 'all'
Requires-Dist: python-telegram-bot>=21.0; extra == 'all'
Requires-Dist: sqlalchemy>=2.0.0; extra == 'all'
Requires-Dist: trafilatura>=1.6.0; extra == 'all'
Provides-Extra: all-experimental
Requires-Dist: beautifulsoup4>=4.12.0; extra == 'all-experimental'
Requires-Dist: google-api-python-client<3.0.0,>=2.100.0; extra == 'all-experimental'
Requires-Dist: google-auth-oauthlib<2.0.0,>=1.2.0; extra == 'all-experimental'
Requires-Dist: google-auth<3.0.0,>=2.25.0; extra == 'all-experimental'
Requires-Dist: google-cloud-aiplatform>=1.0.0; extra == 'all-experimental'
Requires-Dist: google-cloud-discoveryengine>=0.13.0; extra == 'all-experimental'
Requires-Dist: google-cloud-firestore>=2.16.0; extra == 'all-experimental'
Requires-Dist: google-cloud-storage>=3.0.0; extra == 'all-experimental'
Requires-Dist: google-genai>=1.0.0; extra == 'all-experimental'
Requires-Dist: langchain-google-community>=2.0.0; extra == 'all-experimental'
Requires-Dist: langchain-google-genai>=2.0.0; extra == 'all-experimental'
Requires-Dist: langchain-google-vertexai>=2.0.0; extra == 'all-experimental'
Requires-Dist: langfuse>=2.0.0; extra == 'all-experimental'
Requires-Dist: networkx>=3.0; extra == 'all-experimental'
Requires-Dist: opentelemetry-instrumentation-threading>=0.48b0; extra == 'all-experimental'
Requires-Dist: psycopg-pool>=3.2.0; extra == 'all-experimental'
Requires-Dist: psycopg[binary]>=3.1.0; extra == 'all-experimental'
Requires-Dist: pymupdf-layout>=0.0.0; extra == 'all-experimental'
Requires-Dist: pymupdf4llm>=0.0.10; extra == 'all-experimental'
Requires-Dist: python-telegram-bot>=21.0; extra == 'all-experimental'
Requires-Dist: sqlalchemy>=2.0.0; extra == 'all-experimental'
Requires-Dist: trafilatura>=1.6.0; extra == 'all-experimental'
Provides-Extra: dev
Requires-Dist: alembic>=1.13.0; extra == 'dev'
Requires-Dist: build>=1.0.0; extra == 'dev'
Requires-Dist: joblib>=1.4.0; extra == 'dev'
Requires-Dist: pre-commit>=3.0.0; extra == 'dev'
Requires-Dist: pytest>=8.0.0; extra == 'dev'
Requires-Dist: ruff>=0.14.0; extra == 'dev'
Requires-Dist: twine>=5.0.0; extra == 'dev'
Provides-Extra: hf-embeddings
Requires-Dist: sentence-transformers>=3.0.0; extra == 'hf-embeddings'
Provides-Extra: hf-transformers
Requires-Dist: torch>=2.0.0; extra == 'hf-transformers'
Requires-Dist: transformers>=4.30.0; extra == 'hf-transformers'
Provides-Extra: ingestion
Requires-Dist: beautifulsoup4>=4.12.0; extra == 'ingestion'
Requires-Dist: networkx>=3.0; extra == 'ingestion'
Requires-Dist: pymupdf-layout>=0.0.0; extra == 'ingestion'
Requires-Dist: pymupdf4llm>=0.0.10; extra == 'ingestion'
Requires-Dist: trafilatura>=1.6.0; extra == 'ingestion'
Provides-Extra: integrations
Requires-Dist: google-api-python-client<3.0.0,>=2.100.0; extra == 'integrations'
Requires-Dist: google-auth-oauthlib<2.0.0,>=1.2.0; extra == 'integrations'
Requires-Dist: google-auth<3.0.0,>=2.25.0; extra == 'integrations'
Requires-Dist: python-telegram-bot>=21.0; extra == 'integrations'
Provides-Extra: models
Requires-Dist: huggingface-hub>=0.20.0; extra == 'models'
Requires-Dist: langchain-anthropic>=0.1.0; extra == 'models'
Requires-Dist: langchain-openai>=0.1.0; extra == 'models'
Provides-Extra: models-anthropic
Requires-Dist: langchain-anthropic>=0.1.0; extra == 'models-anthropic'
Provides-Extra: models-hf-hub
Requires-Dist: huggingface-hub>=0.20.0; extra == 'models-hf-hub'
Provides-Extra: models-openai
Requires-Dist: langchain-openai>=0.1.0; extra == 'models-openai'
Provides-Extra: observability
Requires-Dist: langfuse>=2.0.0; extra == 'observability'
Requires-Dist: opentelemetry-instrumentation-threading>=0.48b0; extra == 'observability'
Provides-Extra: storage
Requires-Dist: google-cloud-firestore>=2.16.0; extra == 'storage'
Requires-Dist: google-cloud-storage>=3.0.0; extra == 'storage'
Requires-Dist: psycopg-pool>=3.2.0; extra == 'storage'
Requires-Dist: psycopg[binary]>=3.1.0; extra == 'storage'
Requires-Dist: sqlalchemy>=2.0.0; extra == 'storage'
Provides-Extra: vertex
Requires-Dist: google-cloud-aiplatform>=1.0.0; extra == 'vertex'
Requires-Dist: google-cloud-discoveryengine>=0.13.0; extra == 'vertex'
Requires-Dist: google-genai>=1.0.0; extra == 'vertex'
Requires-Dist: langchain-google-community>=2.0.0; extra == 'vertex'
Requires-Dist: langchain-google-genai>=2.0.0; extra == 'vertex'
Requires-Dist: langchain-google-vertexai>=2.0.0; extra == 'vertex'
